pykumo/__init__.py
pykumo/const.py
pykumo/py_kumo.py
pykumo/py_kumo_base.py
pykumo/py_kumo_cloud_account.py
pykumo/py_kumo_station.py
pykumo/schedule.py
pykumo-0.3.11.dist-info/licenses/LICENSE
pykumo-0.3.11.dist-info/METADATA
pykumo-0.3.11.dist-info/WHEEL
pykumo-0.3.11.dist-info/top_level.txt
pykumo-0.3.11.dist-info/RECORD
