Metadata-Version: 2.4
Name: pykumo
Version: 0.3.11
Summary: Small library for interfacing with Mitsubishi KumoCloud enabled devices
Home-page: https://github.com/dlarrick/pykumo
Author: Doug Larrick
Author-email: doug@parkercat.org
Classifier: Programming Language :: Python :: 3
Classifier: License :: OSI Approved :: MIT License
Classifier: Operating System :: OS Independent
License-File: LICENSE
Requires-Dist: requests
Requires-Dist: urllib3
Dynamic: author
Dynamic: author-email
Dynamic: classifier
Dynamic: description
Dynamic: description-content-type
Dynamic: home-page
Dynamic: license-file
Dynamic: requires-dist
Dynamic: summary
